engineer_your_data-0.1.3.dist-info/licenses/LICENSE
src/__init__.py
src/__main__.py
src/server.py
src/tools/__init__.py
src/tools/api_client.py
src/tools/base.py
src/tools/data_transformation.py
src/tools/data_validation.py
src/tools/file_operations.py
src/tools/registry.py
src/tools/schema_introspection.py
src/tools/tool_chaining.py
src/tools/visualization.py
src/utils/__init__.py
src/utils/decorators.py
src/utils/helpers.py
src/utils/logging.py
engineer_your_data-0.1.3.dist-info/METADATA
engineer_your_data-0.1.3.dist-info/WHEEL
engineer_your_data-0.1.3.dist-info/entry_points.txt
engineer_your_data-0.1.3.dist-info/top_level.txt
engineer_your_data-0.1.3.dist-info/RECORD
