Metadata-Version: 2.4
Name: engineer-your-data
Version: 0.1.3
Summary: MCP server for data engineering and business intelligence operations
Author-email: Huzaifa Shaikh <190477365+eghuzefa@users.noreply.github.com>
License: MIT
Project-URL: Homepage, https://github.com/eghuzefa/engineer-your-data-mcp
Project-URL: Repository, https://github.com/eghuzefa/engineer-your-data-mcp
Project-URL: Documentation, https://github.com/eghuzefa/engineer-your-data-mcp#readme
Project-URL: Issues, https://github.com/eghuzefa/engineer-your-data-mcp/issues
Keywords: mcp,model-context-protocol,data-engineering,business-intelligence,data-transformation,data-validation,etl,data-quality,claude,ai-assistant
Classifier: Development Status :: 3 - Alpha
Classifier: Intended Audience :: Developers
Classifier: Intended Audience :: Science/Research
Classifier: License :: OSI Approved :: MIT License
Classifier: Programming Language :: Python :: 3
Classifier: Programming Language :: Python :: 3.9
Classifier: Programming Language :: Python :: 3.10
Classifier: Programming Language :: Python :: 3.11
Classifier: Programming Language :: Python :: 3.12
Classifier: Topic :: Software Development :: Libraries :: Python Modules
Classifier: Topic :: Scientific/Engineering :: Information Analysis
Requires-Python: >=3.9
License-File: LICENSE
Requires-Dist: mcp>=1.0.0
Requires-Dist: pandas>=2.0.0
Requires-Dist: numpy>=1.24.0
Requires-Dist: scikit-learn>=1.3.0
Requires-Dist: matplotlib>=3.7.0
Requires-Dist: seaborn>=0.12.0
Requires-Dist: scipy>=1.10.0
Requires-Dist: openpyxl>=3.1.0
Requires-Dist: fastparquet>=0.8.0
Requires-Dist: pydantic>=2.0.0
Requires-Dist: loguru>=0.7.0
Requires-Dist: aiohttp>=3.8.0
Provides-Extra: dev
Requires-Dist: pytest>=7.4.0; extra == "dev"
Requires-Dist: pytest-asyncio>=0.21.0; extra == "dev"
Requires-Dist: aioresponses>=0.7.0; extra == "dev"
Requires-Dist: black>=25.9.0; extra == "dev"
Requires-Dist: flake8>=6.0.0; extra == "dev"
Requires-Dist: pytest-cov>=4.1.0; extra == "dev"
Dynamic: license-file
